<?xml version="1.0" encoding="UTF-8"?>
<openerp>
	<data>
	
		<record id="view_picking_form" model="ir.ui.view">
			<field name="name">stock.picking.form</field>
			<field name="model">stock.picking</field>
			<field name="type">form</field>
			<field eval="12" name="priority"/>
			<field name="inherit_id" ref="stock.view_picking_form"/>
			<field name="arch" type="xml">
				<button name="action_process" position="before">
					<button name="start_acquisition" string="Start Acquisition" states="assigned,confirmed,draft" type="object" icon="gtk-go-forward"/>
				</button>
			</field>
		</record>
		
        <record id="view_delivery_order_inherit_stock_barcode" model="ir.ui.view">
            <field name="name">stock.picking.out.barcode.form</field>
            <field name="type">form</field>
            <field name="model">stock.picking</field>
            <field name="inherit_id" ref="stock.view_picking_out_form"/>
            <field name="arch" type="xml">                
				<button name="action_process" position="before">
					<button name="start_acquisition" string="Start Acquisition" states="assigned,confirmed,draft" type="object" icon="gtk-go-forward"/>
				</button>
            </field>
        </record>
   
	</data>
</openerp>